alfred/__init__.py
alfred/alfred_command.py
alfred/alfred_prompt.py
alfred/cli.py
alfred/commands.py
alfred/ctx.py
alfred/decorator.py
alfred/domain/__init__.py
alfred/domain/command.py
alfred/domain/manifest.py
alfred/domain/project.py
alfred/echo.py
alfred/exceptions.py
alfred/interpreter.py
alfred/lib.py
alfred/logger.py
alfred/main.py
alfred/manifest.py
alfred/middlewares.py
alfred/os.py
alfred/process.py
alfred/project.py
alfred/resource.py
alfred/resources/.alfred.toml
alfred/resources/__init__.py
alfred/resources/bash
alfred/resources/cmd.py
alfred/resources/command_module_existing.tpl
alfred/resources/command_module_new.tpl
alfred/resources/command_presentation.tpl
alfred/resources/fish
alfred/resources/zsh
alfred/self_command.py
alfred/shell_completion.py
alfred/venv_plugins/__init__.py
alfred/venv_plugins/base.py
alfred/venv_plugins/dotvenv.py
alfred/venv_plugins/poetry.py
alfred/venv_plugins/venv.py
alfred_cli-2.2.7.dist-info/LICENSE
alfred_cli-2.2.7.dist-info/METADATA
alfred_cli-2.2.7.dist-info/WHEEL
alfred_cli-2.2.7.dist-info/entry_points.txt
alfred_cli-2.2.7.dist-info/RECORD
