Metadata-Version: 2.1
Name: alfred-cli
Version: 2.2.7
Summary: Alfred is an extensible automation tool. It allows you to build your continuous integration scripts in python, and much more. You can replace any scripts using the best of both worlds, shell and python.
Home-page: https://github.com/FabienArcellier/alfred-cli#alfred
License: MIT
Keywords: building tool,makefile,productivity,automation,continuous integration,developper friendly
Author: Fabien Arcellier
Author-email: fabien.arcellier@gmail.com
Requires-Python: >=3.8,<4.0
Classifier: Development Status :: 4 - Beta
Classifier: Intended Audience :: Developers
Classifier: License :: OSI Approved :: MIT License
Classifier: Operating System :: OS Independent
Classifier: Programming Language :: Python :: 3
Classifier: Programming Language :: Python :: 3.8
Classifier: Programming Language :: Python :: 3.9
Classifier: Programming Language :: Python :: 3.10
Classifier: Programming Language :: Python :: 3.11
Classifier: Programming Language :: Python :: 3.12
Classifier: Topic :: Software Development :: Build Tools
Classifier: Topic :: Software Development :: Testing
Requires-Dist: click (>=8.1.0,<9.0.0)
Requires-Dist: prompt-toolkit (>=3.0.41,<4.0.0)
Requires-Dist: shellingham (>=1.3.0,<2.0.0)
Requires-Dist: toml (>=0.10,<0.11)
Project-URL: Documentation, https://alfred-cli.readthedocs.io/en/latest
Project-URL: Repository, https://github.com/FabienArcellier/alfred-cli
